Metadata-Version: 2.4
Name: coastsat_package
Version: 0.3.4
Summary: A packaged version of CoastSat: A Global shoreline mapping tool from satellite imagery
Author: Sharon Fitzpatrick
Project-URL: Homepage, https://github.com/SatelliteShorelines/coastsat_package
Project-URL: Bug Tracker, https://github.com/SatelliteShorelines/coastsat_package/issues
Classifier: Programming Language :: Python :: 3
Classifier: License :: OSI Approved :: MIT License
Classifier: Operating System :: OS Independent
Requires-Python: >=3.8
License-File: LICENSE.md
Requires-Dist: scikit-image
Requires-Dist: earthengine-api>=0.1.304
Requires-Dist: jupyterlab>=3.0.0
Requires-Dist: geopandas
Requires-Dist: matplotlib
Requires-Dist: astropy
Requires-Dist: tqdm
Requires-Dist: importlib-resources
Requires-Dist: pyqt5
Requires-Dist: scipy
Requires-Dist: numpy
Requires-Dist: imageio
Requires-Dist: scikit-learn
Dynamic: description
Dynamic: description-content-type
Dynamic: license-file
